Metadata-Version: 1.0
Name: Kashi-distributions
Version: 1.2
Summary: Gaussian and Binomial distributions
Home-page: UNKNOWN
Author: Kashi Sankhla
Author-email: kashisankhla2105@gmail.com
License: UNKNOWN
Platform: UNKNOWN
